datastreamcorelib/__init__.py
datastreamcorelib/abstract.py
datastreamcorelib/binpackers.py
datastreamcorelib/datamessage.py
datastreamcorelib/imagemessage.py
datastreamcorelib/logging.py
datastreamcorelib/pubsub.py
datastreamcorelib/py.typed
datastreamcorelib/reqrep.py
datastreamcorelib/testhelpers.py
datastreamcorelib/utils.py
datastreamcorelib-1.7.1.dist-info/LICENSE
datastreamcorelib-1.7.1.dist-info/METADATA
datastreamcorelib-1.7.1.dist-info/WHEEL
datastreamcorelib-1.7.1.dist-info/RECORD
