Metadata-Version: 2.3
Name: datastreamcorelib
Version: 1.7.1
Summary: Helpers and utilities for https://gitlab.com/advian-oss/python-datastreamservicelib that are not eventloop specific.
License: MIT
Author: Eero af Heurlin
Author-email: eero.afheurlin@iki.fi
Requires-Python: >=3.9,<4.0
Classifier: License :: OSI Approved :: MIT License
Classifier: Programming Language :: Python :: 3
Classifier: Programming Language :: Python :: 3.9
Classifier: Programming Language :: Python :: 3.10
Classifier: Programming Language :: Python :: 3.11
Classifier: Programming Language :: Python :: 3.12
Classifier: Programming Language :: Python :: 3.13
Requires-Dist: libadvian (>=0.3,<=2.0)
Requires-Dist: msgpack (>=1.0,<2.0)
